aiotelnet/__init__.py
aiotelnet/client.py
aiotelnet-1.1.0.dist-info/licenses/LICENSE
aiotelnet-1.1.0.dist-info/WHEEL
aiotelnet-1.1.0.dist-info/METADATA
aiotelnet-1.1.0.dist-info/RECORD
