Metadata-Version: 2.4
Name: aiotelnet
Version: 1.1.0
Summary: A generic asyncio Python package to use telnet.
Author-email: Jordan Harvey <jordan@hrvy.uk>
Requires-Python: >=3.13.0
Classifier: Development Status :: 3 - Alpha
Classifier: Intended Audience :: Developers
Classifier: License :: OSI Approved :: MIT License
Classifier: Programming Language :: Python :: 3 :: Only
Classifier: Programming Language :: Python :: 3.13
Classifier: Programming Language :: Python :: 3.14
License-File: LICENSE
Requires-Dist: bandit[toml]==1.7.5 ; extra == "test"
Requires-Dist: black==23.3.0 ; extra == "test"
Requires-Dist: check-manifest==0.49 ; extra == "test"
Requires-Dist: flake8-bugbear==23.5.9 ; extra == "test"
Requires-Dist: flake8-docstrings ; extra == "test"
Requires-Dist: flake8-formatter_junit_xml ; extra == "test"
Requires-Dist: flake8 ; extra == "test"
Requires-Dist: flake8-pyproject ; extra == "test"
Requires-Dist: pre-commit==3.3.1 ; extra == "test"
Requires-Dist: pylint==2.17.4 ; extra == "test"
Requires-Dist: pylint_junit ; extra == "test"
Requires-Dist: pytest-cov==7.0.0 ; extra == "test"
Requires-Dist: pytest-mock>=3.14.0 ; extra == "test"
Requires-Dist: pytest-runner ; extra == "test"
Requires-Dist: pytest-asyncio ; extra == "test"
Requires-Dist: pytest>=8.0.0 ; extra == "test"
Requires-Dist: pytest-github-actions-annotate-failures ; extra == "test"
Requires-Dist: shellcheck-py==0.9.0.2 ; extra == "test"
Project-URL: Documentation, https://github.com/pantherale0/aiotelnet
Project-URL: Source, https://github.com/pantherale0/aiotelnet
Project-URL: Tracker, https://github.com/pantherale0/aiotelnet/issues
Provides-Extra: test
